{
  "header": "<h1>תהילים פרק יז</h1>",
  "verses": [
    "<b>א</b>",
    " תְּפִלָּ֗ה לְדָ֫וִ֥ד",
    "<br>",
    "שִׁמְעָ֤ה יְהוָ֨ה&nbsp;׀ צֶ֗דֶק &nbsp;&nbsp; הַקְשִׁ֥יבָה רִנָּתִ֗י הַֽאֲזִ֥ינָה תְפִלָּתִ֑י",
    "<br>",
    "בְּ֝לֹ֗א &nbsp;&nbsp; שִׂפְתֵ֥י מִרְמָֽה׃",
    "<br>",
    "<a name=\"2\"> </a>",
    "<b>ב</b>",
    " מִ֭לְּפָנֶיךָ מִשְׁפָּטִ֣י יֵצֵ֑א &nbsp;&nbsp; עֵ֝ינֶ֗יךָ תֶּֽחֱזֶ֥ינָה מֵֽישָׁרִֽים׃",
    "<br>",
    "<a name=\"3\"> </a>",
    "<b>ג</b>",
    " בָּ֘חַ֤נְתָּ לִבִּ֨י&nbsp;׀ פָּ֘קַ֤דְתָּ לַּ֗יְלָה &nbsp;&nbsp; צְרַפְתַּ֥נִי בַל־תִּמְצָ֑א",
    "<br>",
    "זַ֝מֹּתִ֗י &nbsp;&nbsp; בַּל־יַֽעֲבָר־פִּֽי׃",
    "<br>",
    "<a name=\"4\"> </a>",
    "<b>ד</b>",
    " לִפְעֻלּ֣וֹת אָ֭דָם בִּדְבַ֣ר שְׂפָתֶ֑יךָ &nbsp;&nbsp; אֲנִ֥י שָׁ֝מַ֗רְתִּי אָרְח֥וֹת פָּרִֽיץ׃",
    "<br>",
    "<a name=\"5\"> </a>",
    "<b>ה</b>",
    " תָּמֹ֣ךְ אֲ֭שֻׁרַי בְּמַעְגְּלוֹתֶ֑יךָ &nbsp;&nbsp; בַּל־נָמ֥וֹטּוּ פְעָמָֽי׃",
    "<br>",
    "<a name=\"6\"> </a>",
    "<b>ו</b>",
    " אֲנִֽי־קְרָאתִ֣יךָ כִֽי־תַעֲנֵ֣נִי אֵ֑ל &nbsp;&nbsp; הַֽט־אָזְנְךָ֥ לִ֝֗י שְׁמַ֣ע אִמְרָתִֽי׃",
    "<br>",
    "<a name=\"7\"> </a>",
    "<b>ז</b>",
    " הַפְלֵ֣ה חֲ֭סָדֶיךָ מוֹשִׁ֣יעַ חוֹסִ֑ים &nbsp;&nbsp; מִ֝מִּתְקֽוֹמְמִ֗ים בִּֽימִינֶֽךָ׃",
    "<br>",
    "<a name=\"8\"> </a>",
    "<b>ח</b>",
    " שָׁ֭מְרֵנִי כְּאִישׁ֣וֹן בַּת־עָ֑יִן &nbsp;&nbsp; בְּצֵ֥ל כְּ֝נָפֶ֗יךָ תַּסְתִּירֵֽנִי׃",
    "<br>",
    "<a name=\"9\"> </a>",
    "<b>ט</b>",
    " מִפְּנֵ֣י רְ֭שָׁעִים ז֣וּ שַׁדּ֑וּנִי &nbsp;&nbsp; אֹֽיְבַ֥י בְּ֝נֶ֗פֶשׁ יַקִּ֥יפוּ עָלָֽי׃",
    "<br>",
    "<a name=\"10\"> </a>",
    "<b>י</b>",
    " חֶלְבָּ֥מוֹ סָּֽגְר֑וּ &nbsp;&nbsp; פִּ֝֗ימוֹ דִּבְּר֥וּ בְגֵאֽוּת׃",
    "<br>",
    "<a name=\"11\"> </a>",
    "<b>יא</b>",
    " אַ֭שֻּׁרֵינוּ עַתָּ֣ה סבבוני ",
    "<span class=\"qri\">סְבָב֑וּנוּ</span>",
    " &nbsp;&nbsp; עֵֽינֵיהֶ֥ם יָ֝שִׁ֗יתוּ לִנְט֥וֹת בָּאָֽרֶץ׃",
    "<br>",
    "<a name=\"12\"> </a>",
    "<b>יב</b>",
    " דִּמְיֹנ֗וֹ כְּ֭אַרְיֵה יִכְס֣וֹף לִטְרֹ֑ף &nbsp;&nbsp; וְ֝כִכְפִ֗יר יֹשֵׁ֥ב בְּמִסְתָּרִֽים׃",
    "<br>",
    "<a name=\"13\"> </a>",
    "<b>יג</b>",
    " קוּמָ֤ה יְהוָ֗ה &nbsp;&nbsp; קַדְּמָ֣ה פָ֭נָיו הַכְרִיעֵ֑הוּ",
    "<br>",
    "פַּלְּטָ֥ה נַ֝פְשִׁ֗י &nbsp;&nbsp; מֵֽרָשָׁ֥ע חַרְבֶּֽךָ׃",
    "<br>",
    "<a name=\"14\"> </a>",
    "<b>יד</b>",
    " מִ֥מְתִֽים יָֽדְךָ֨&nbsp;׀ יְהוָ֡ה &nbsp;&nbsp; מִֽמְתִ֬ים מֵחֶ֗לֶד ",
    "<br>",
    "חֶלְקָ֥ם בַּֽחַיִּים֮ &nbsp;&nbsp; וצפינך ",
    "<span class=\"qri\">וּֽצְפוּנְךָ֮</span>",
    " תְּמַלֵּ֪א בִ֫טְנָ֥ם",
    "<br>",
    "יִשְׂבְּע֥וּ בָנִ֑ים &nbsp;&nbsp; וְהִנִּ֥יחוּ יִ֝תְרָ֗ם לְעֽוֹלְלֵיהֶֽם׃",
    "<br>",
    "<a name=\"15\"> </a>",
    "<b>טו</b>",
    " אֲנִ֗י בְּ֭צֶדֶק אֶֽחֱזֶ֣ה פָנֶ֑יךָ &nbsp;&nbsp; אֶשְׂבְּעָ֥ה בְ֝הָקִ֗יץ תְּמֽוּנָתֶֽךָ׃"
  ],
  "lines": [
    {
      "verse": "א",
      "text": "תְּפִלָּ֗ה לְדָ֫וִ֥ד שִׁמְעָ֤ה יְהוָ֨ה ׀ צֶ֗דֶק הַקְשִׁ֥יבָה רִנָּתִ֗י הַֽאֲזִ֥ינָה תְפִלָּתִ֑י בְּ֝לֹ֗א שִׂפְתֵ֥י מִרְמָֽה"
    },
    {
      "verse": "ב",
      "text": "מִ֭לְּפָנֶיךָ מִשְׁפָּטִ֣י יֵצֵ֑א עֵ֝ינֶ֗יךָ תֶּֽחֱזֶ֥ינָה מֵֽישָׁרִֽים"
    },
    {
      "verse": "ג",
      "text": "בָּ֘חַ֤נְתָּ לִבִּ֨י ׀ פָּ֘קַ֤דְתָּ לַּ֗יְלָה צְרַפְתַּ֥נִי בַל־תִּמְצָ֑א זַ֝מֹּתִ֗י בַּל־יַֽעֲבָר־פִּֽי"
    },
    {
      "verse": "ד",
      "text": "לִפְעֻלּ֣וֹת אָ֭דָם בִּדְבַ֣ר שְׂפָתֶ֑יךָ אֲנִ֥י שָׁ֝מַ֗רְתִּי אָרְח֥וֹת פָּרִֽיץ"
    },
    {
      "verse": "ה",
      "text": "תָּמֹ֣ךְ אֲ֭שֻׁרַי בְּמַעְגְּלוֹתֶ֑יךָ בַּל־נָמ֥וֹטּוּ פְעָמָֽי"
    },
    {
      "verse": "ו",
      "text": "אֲנִֽי־קְרָאתִ֣יךָ כִֽי־תַעֲנֵ֣נִי אֵ֑ל הַֽט־אָזְנְךָ֥ לִ֝֗י שְׁמַ֣ע אִמְרָתִֽי"
    },
    {
      "verse": "ז",
      "text": "הַפְלֵ֣ה חֲ֭סָדֶיךָ מוֹשִׁ֣יעַ חוֹסִ֑ים מִ֝מִּתְקֽוֹמְמִ֗ים בִּֽימִינֶֽךָ"
    },
    {
      "verse": "ח",
      "text": "שָׁ֭מְרֵנִי כְּאִישׁ֣וֹן בַּת־עָ֑יִן בְּצֵ֥ל כְּ֝נָפֶ֗יךָ תַּסְתִּירֵֽנִי"
    },
    {
      "verse": "ט",
      "text": "מִפְּנֵ֣י רְ֭שָׁעִים ז֣וּ שַׁדּ֑וּנִי אֹֽיְבַ֥י בְּ֝נֶ֗פֶשׁ יַקִּ֥יפוּ עָלָֽי"
    },
    {
      "verse": "י",
      "text": "חֶלְבָּ֥מוֹ סָּֽגְר֑וּ פִּ֝֗ימוֹ דִּבְּר֥וּ בְגֵאֽוּת"
    },
    {
      "verse": "יא",
      "text": "אַ֭שֻּׁרֵינוּ עַתָּ֣ה סבבוני <span class=\"qri\">סְבָב֑וּנוּ</span> עֵֽינֵיהֶ֥ם יָ֝שִׁ֗יתוּ לִנְט֥וֹת בָּאָֽרֶץ"
    },
    {
      "verse": "יב",
      "text": "דִּמְיֹנ֗וֹ כְּ֭אַרְיֵה יִכְס֣וֹף לִטְרֹ֑ף וְ֝כִכְפִ֗יר יֹשֵׁ֥ב בְּמִסְתָּרִֽים"
    },
    {
      "verse": "יג",
      "text": "קוּמָ֤ה יְהוָ֗ה קַדְּמָ֣ה פָ֭נָיו הַכְרִיעֵ֑הוּ פַּלְּטָ֥ה נַ֝פְשִׁ֗י מֵֽרָשָׁ֥ע חַרְבֶּֽךָ"
    },
    {
      "verse": "יד",
      "text": "מִ֥מְתִֽים יָֽדְךָ֨ ׀ יְהוָ֡ה מִֽמְתִ֬ים מֵחֶ֗לֶד חֶלְקָ֥ם בַּֽחַיִּים֮ וצפינך <span class=\"qri\">וּֽצְפוּנְךָ֮</span> תְּמַלֵּ֪א בִ֫טְנָ֥ם יִשְׂבְּע֥וּ בָנִ֑ים וְהִנִּ֥יחוּ יִ֝תְרָ֗ם לְעֽוֹלְלֵיהֶֽם"
    },
    {
      "verse": "טו",
      "text": "אֲנִ֗י בְּ֭צֶדֶק אֶֽחֱזֶ֣ה פָנֶ֑יךָ אֶשְׂבְּעָ֥ה בְ֝הָקִ֗יץ תְּמֽוּנָתֶֽךָ"
    }
  ],
  "perk": "יז"
}