{
  "header": "<h1>תהילים פרק מה</h1>",
  "verses": [
    "<b>א</b>",
    " לַמְנַצֵּ֣חַ עַל־שֹֽׁ֭שַׁנִּים לִבְנֵי־קֹ֑רַח &nbsp;&nbsp; מַ֝שְׂכִּ֗יל שִׁ֣יר יְדִידֹֽת׃",
    "<br>",
    "<a name=\"2\"> </a>",
    "<b>ב</b>",
    " רָ֘חַ֤שׁ לִבִּ֨י&nbsp;׀ דָּ֘בָ֤ר ט֗וֹב &nbsp;&nbsp; אֹמֵ֣ר אָ֭נִי מַֽעֲשַׂ֣י לְמֶ֑לֶךְ",
    "<br>",
    "לְ֝שׁוֹנִ֗י &nbsp;&nbsp; עֵ֤ט&nbsp;׀ סוֹפֵ֬ר מָהִֽיר׃",
    "<br>",
    "<a name=\"3\"> </a>",
    "<b>ג</b>",
    " יָפְיָפִ֡יתָ מִבְּנֵ֬י אָדָ֗ם &nbsp;&nbsp; ה֣וּצַק חֵ֭ן בְּשִׂפְתוֹתֶ֑יךָ",
    "<br>",
    "עַל־כֵּ֤ן בֵּֽרַכְךָ֖ אֱלֹהִ֣ים &nbsp;&nbsp; לְעוֹלָֽם׃",
    "<br>",
    "<a name=\"4\"> </a>",
    "<b>ד</b>",
    " חֲגֽוֹר־חַרְבְּךָ֣ עַל־יָרֵ֣ךְ גִּבּ֑וֹר &nbsp;&nbsp; הֽ֝וֹדְךָ֗ וַֽהֲדָרֶֽךָ׃",
    "<br>",
    "<a name=\"5\"> </a>",
    "<b>ה</b>",
    " וַהֲדָ֬רְךָ֨&nbsp;׀ צְלַ֬ח רְכַ֗ב &nbsp;&nbsp; עַֽל־דְּבַר־אֱ֭מֶת וְעַנְוָה־צֶ֑דֶק",
    "<br>",
    "וְתֽוֹרְךָ֖ נֽוֹרָא֣וֹת &nbsp;&nbsp; יְמִינֶֽךָ׃",
    "<br>",
    "<a name=\"6\"> </a>",
    "<b>ו</b>",
    " חִצֶּ֗יךָ שְׁנ֫וּנִ֥ים &nbsp;&nbsp; עַ֭מִּים תַּחְתֶּ֣יךָ יִפְּל֑וּ בְּ֝לֵ֗ב אֽוֹיְבֵ֥י הַמֶּֽלֶךְ׃",
    "<br>",
    "<a name=\"7\"> </a>",
    "<b>ז</b>",
    " כִּסְאֲךָ֣ אֱ֭לֹהִים עוֹלָ֣ם וָעֶ֑ד &nbsp;&nbsp; שֵׁ֥בֶט מִ֝ישֹׁ֗ר שֵׁ֣בֶט מַלְכוּתֶֽךָ׃",
    "<br>",
    "<a name=\"8\"> </a>",
    "<b>ח</b>",
    " אָהַ֣בְתָּ צֶּדֶק֮ &nbsp;&nbsp; וַתִּשְׂנָ֫א רֶ֥שַׁע",
    "<br>",
    "עַל־כֵּ֤ן&nbsp;׀ מְשָֽׁחֲךָ֡ אֱלֹהִ֣ים אֱ֭לֹהֶיךָ שֶׁ֥מֶן שָׂשׂ֗וֹן &nbsp;&nbsp; מֵֽחֲבֵרֶֽךָ׃",
    "<br>",
    "<a name=\"9\"> </a>",
    "<b>ט</b>",
    " מֹר־וַֽאֲהָל֣וֹת קְ֭צִיעוֹת כָּל־בִּגְדֹתֶ֑יךָ &nbsp;&nbsp; מִֽן־הֵ֥יכְלֵי שֵׁ֝֗ן מִנִּ֥י שִׂמְּחֽוּךָ׃",
    "<br>",
    "<a name=\"10\"> </a>",
    "<b>י</b>",
    " בְּנ֣וֹת מְ֭לָכִים בְּיִקְּרוֹתֶ֑יךָ &nbsp;&nbsp; נִצְּבָ֥ה שֵׁגַ֥ל לִ֝ימִֽינְךָ֗ בְּכֶ֣תֶם אוֹפִֽיר׃",
    "<br>",
    "<a name=\"11\"> </a>",
    "<b>יא</b>",
    " שִׁמְעִי־בַ֣ת וּ֭רְאִי וְהַטִּ֣י אָזְנֵ֑ךְ &nbsp;&nbsp; וְשִׁכְחִ֥י עַ֝מֵּ֗ךְ וּבֵ֥ית אָבִֽיךְ׃",
    "<br>",
    "<a name=\"12\"> </a>",
    "<b>יב</b>",
    " וְיִתְאָ֣ו הַמֶּ֣לֶךְ יָפְיֵ֑ךְ &nbsp;&nbsp; כִּי־ה֥וּא אֲ֝דֹנַ֗יִךְ וְהִשְׁתַּֽחֲוִי־לֽוֹ׃",
    "<br>",
    "<a name=\"13\"> </a>",
    "<b>יג</b>",
    " וּבַֽת־צֹ֨ר&nbsp;׀ &nbsp;&nbsp; בְּ֭מִנְחָה פָּנַ֥יִךְ יְחַלּ֗וּ עֲשִׁ֣ירֵי עָֽם׃",
    "<br>",
    "<a name=\"14\"> </a>",
    "<b>יד</b>",
    " כָּל־כְּבוּדָּ֣ה בַת־מֶ֣לֶךְ פְּנִ֑ימָה &nbsp;&nbsp; מִֽמִּשְׁבְּצ֖וֹת זָהָ֣ב לְבוּשָֽׁהּ׃",
    "<br>",
    "<a name=\"15\"> </a>",
    "<b>טו</b>",
    " לִרְקָמוֹת֮ תּוּבַ֪ל לַ֫מֶּ֥לֶךְ &nbsp;&nbsp; בְּתוּל֣וֹת אַֽ֭חֲרֶיהָ רֵֽעוֹתֶ֑יהָ מ֖וּבָא֣וֹת לָֽךְ׃",
    "<br>",
    "<a name=\"16\"> </a>",
    "<b>טז</b>",
    " תּ֭וּבַלְנָה בִּשְׂמָחֹ֣ת וָגִ֑יל &nbsp;&nbsp; תְּ֝בֹאֶ֗ינָה בְּהֵ֣יכַל מֶֽלֶךְ׃",
    "<br>",
    "<a name=\"17\"> </a>",
    "<b>יז</b>",
    " תַּ֣חַת אֲ֭בֹתֶיךָ יִֽהְי֣וּ בָנֶ֑יךָ &nbsp;&nbsp; תְּשִׁיתֵ֥מוֹ לְ֝שָׂרִ֗ים בְּכָל־הָאָֽרֶץ׃",
    "<br>",
    "<a name=\"18\"> </a>",
    "<b>יח</b>",
    " אַזְכִּ֣ירָה שִׁ֭מְךָ בְּכָל־דֹּ֣ר וָדֹ֑ר &nbsp;&nbsp; עַל־כֵּ֥ן עַמִּ֥ים יְ֝הוֹדוּ֗ךָ לְעֹלָ֥ם וָעֶֽד׃"
  ],
  "lines": [
    {
      "verse": "א",
      "text": "לַמְנַצֵּ֣חַ עַל־שֹֽׁ֭שַׁנִּים לִבְנֵי־קֹ֑רַח מַ֝שְׂכִּ֗יל שִׁ֣יר יְדִידֹֽת",
      "worCount": 6,
      "progressStart": 0,
      "startTime": 0,
      "progressEnd": 6,
      "endTime": 7.339341918367347
    },
    {
      "verse": "ב",
      "text": "רָ֘חַ֤שׁ לִבִּ֨י ׀ דָּ֘בָ֤ר ט֗וֹב אֹמֵ֣ר אָ֭נִי מַֽעֲשַׂ֣י לְמֶ֑לֶךְ לְ֝שׁוֹנִ֗י עֵ֤ט ׀ סוֹפֵ֬ר מָהִֽיר",
      "worCount": 14,
      "progressStart": 6,
      "startTime": 7.339341918367347,
      "progressEnd": 16,
      "endTime": 18.756096013605443
    },
    {
      "verse": "ג",
      "text": "יָפְיָפִ֡יתָ מִבְּנֵ֬י אָדָ֗ם ה֣וּצַק חֵ֭ן בְּשִׂפְתוֹתֶ֑יךָ עַל־כֵּ֤ן בֵּֽרַכְךָ֖ אֱלֹהִ֣ים לְעוֹלָֽם",
      "worCount": 10,
      "progressStart": 16,
      "startTime": 18.756096013605443,
      "progressEnd": 22,
      "endTime": 26.91092036734694
    },
    {
      "verse": "ד",
      "text": "חֲגֽוֹר־חַרְבְּךָ֣ עַל־יָרֵ֣ךְ גִּבּ֑וֹר הֽ֝וֹדְךָ֗ וַֽהֲדָרֶֽךָ",
      "worCount": 5,
      "progressStart": 22,
      "startTime": 26.91092036734694,
      "progressEnd": 26,
      "endTime": 30.988332544217688
    },
    {
      "verse": "ה",
      "text": "וַהֲדָ֬רְךָ֨ ׀ צְלַ֬ח רְכַ֗ב עַֽל־דְּבַר־אֱ֭מֶת וְעַנְוָה־צֶ֑דֶק וְתֽוֹרְךָ֖ נֽוֹרָא֣וֹת יְמִינֶֽךָ",
      "worCount": 9,
      "progressStart": 26,
      "startTime": 30.988332544217688,
      "progressEnd": 32,
      "endTime": 38.32767446258504
    },
    {
      "verse": "ו",
      "text": "חִצֶּ֗יךָ שְׁנ֫וּנִ֥ים עַ֭מִּים תַּחְתֶּ֣יךָ יִפְּל֑וּ בְּ֝לֵ֗ב אֽוֹיְבֵ֥י הַמֶּֽלֶךְ",
      "worCount": 8,
      "progressStart": 32,
      "startTime": 38.32767446258504,
      "progressEnd": 37,
      "endTime": 44.85153394557823
    },
    {
      "verse": "ז",
      "text": "כִּסְאֲךָ֣ אֱ֭לֹהִים עוֹלָ֣ם וָעֶ֑ד שֵׁ֥בֶט מִ֝ישֹׁ֗ר שֵׁ֣בֶט מַלְכוּתֶֽךָ",
      "worCount": 8,
      "progressStart": 37,
      "startTime": 44.85153394557823,
      "progressEnd": 43,
      "endTime": 51.37539342857143
    },
    {
      "verse": "ח",
      "text": "אָהַ֣בְתָּ צֶּדֶק֮ וַתִּשְׂנָ֫א רֶ֥שַׁע עַל־כֵּ֤ן ׀ מְשָֽׁחֲךָ֡ אֱלֹהִ֣ים אֱ֭לֹהֶיךָ שֶׁ֥מֶן שָׂשׂ֗וֹן מֵֽחֲבֵרֶֽךָ",
      "worCount": 12,
      "progressStart": 43,
      "startTime": 51.37539342857143,
      "progressEnd": 51,
      "endTime": 61.161182653061225
    },
    {
      "verse": "ט",
      "text": "מֹר־וַֽאֲהָל֣וֹת קְ֭צִיעוֹת כָּל־בִּגְדֹתֶ֑יךָ מִֽן־הֵ֥יכְלֵי שֵׁ֝֗ן מִנִּ֥י שִׂמְּחֽוּךָ",
      "worCount": 7,
      "progressStart": 51,
      "startTime": 61.161182653061225,
      "progressEnd": 56,
      "endTime": 66.86955970068027
    },
    {
      "verse": "י",
      "text": "בְּנ֣וֹת מְ֭לָכִים בְּיִקְּרוֹתֶ֑יךָ נִצְּבָ֥ה שֵׁגַ֥ל לִ֝ימִֽינְךָ֗ בְּכֶ֣תֶם אוֹפִֽיר",
      "worCount": 8,
      "progressStart": 56,
      "startTime": 66.86955970068027,
      "progressEnd": 61,
      "endTime": 73.39341918367347
    },
    {
      "verse": "יא",
      "text": "שִׁמְעִי־בַ֣ת וּ֭רְאִי וְהַטִּ֣י אָזְנֵ֑ךְ וְשִׁכְחִ֥י עַ֝מֵּ֗ךְ וּבֵ֥ית אָבִֽיךְ",
      "worCount": 8,
      "progressStart": 61,
      "startTime": 73.39341918367347,
      "progressEnd": 67,
      "endTime": 79.91727866666666
    },
    {
      "verse": "יב",
      "text": "וְיִתְאָ֣ו הַמֶּ֣לֶךְ יָפְיֵ֑ךְ כִּי־ה֥וּא אֲ֝דֹנַ֗יִךְ וְהִשְׁתַּֽחֲוִי־לֽוֹ",
      "worCount": 6,
      "progressStart": 67,
      "startTime": 79.91727866666666,
      "progressEnd": 71,
      "endTime": 84.81017327891156
    },
    {
      "verse": "יג",
      "text": "וּבַֽת־צֹ֨ר ׀ בְּ֭מִנְחָה פָּנַ֥יִךְ יְחַלּ֗וּ עֲשִׁ֣ירֵי עָֽם",
      "worCount": 7,
      "progressStart": 71,
      "startTime": 84.81017327891156,
      "progressEnd": 76,
      "endTime": 90.5185503265306
    },
    {
      "verse": "יד",
      "text": "כָּל־כְּבוּדָּ֣ה בַת־מֶ֣לֶךְ פְּנִ֑ימָה מִֽמִּשְׁבְּצ֖וֹת זָהָ֣ב לְבוּשָֽׁהּ",
      "worCount": 6,
      "progressStart": 76,
      "startTime": 90.5185503265306,
      "progressEnd": 80,
      "endTime": 95.4114449387755
    },
    {
      "verse": "טו",
      "text": "לִרְקָמוֹת֮ תּוּבַ֪ל לַ֫מֶּ֥לֶךְ בְּתוּל֣וֹת אַֽ֭חֲרֶיהָ רֵֽעוֹתֶ֑יהָ מ֖וּבָא֣וֹת לָֽךְ",
      "worCount": 8,
      "progressStart": 80,
      "startTime": 95.4114449387755,
      "progressEnd": 85,
      "endTime": 101.9353044217687
    },
    {
      "verse": "טז",
      "text": "תּ֭וּבַלְנָה בִּשְׂמָחֹ֣ת וָגִ֑יל תְּ֝בֹאֶ֗ינָה בְּהֵ֣יכַל מֶֽלֶךְ",
      "worCount": 6,
      "progressStart": 85,
      "startTime": 101.9353044217687,
      "progressEnd": 89,
      "endTime": 106.82819903401361
    },
    {
      "verse": "יז",
      "text": "תַּ֣חַת אֲ֭בֹתֶיךָ יִֽהְי֣וּ בָנֶ֑יךָ תְּשִׁיתֵ֥מוֹ לְ֝שָׂרִ֗ים בְּכָל־הָאָֽרֶץ",
      "worCount": 7,
      "progressStart": 89,
      "startTime": 106.82819903401361,
      "progressEnd": 94,
      "endTime": 112.53657608163266
    },
    {
      "verse": "יח",
      "text": "אַזְכִּ֣ירָה שִׁ֭מְךָ בְּכָל־דֹּ֣ר וָדֹ֑ר עַל־כֵּ֥ן עַמִּ֥ים יְ֝הוֹדוּ֗ךָ לְעֹלָ֥ם וָעֶֽד",
      "worCount": 9,
      "progressStart": 94,
      "startTime": 112.53657608163266,
      "progressEnd": 100,
      "endTime": 119.875918
    }
  ],
  "perk": "מה",
  "wordCount": 144,
  "duration": 119.875918
}